{
  "collections": {
    "tomorrowland_winter": {
      "label": "Letter",
      "history": [
        {
          "ts": "2026-07-22T11:20:36.650123+00:00",
          "floor_sol": 44.999,
          "listed": 17,
          "sales_24h": 0
        },
        {
          "ts": "2026-07-22T12:55:52.693012+00:00",
          "floor_sol": 45.899,
          "listed": 17,
          "sales_24h": 0
        },
        {
          "ts": "2026-07-22T12:59:20.715598+00:00",
          "floor_sol": 45.899,
          "listed": 17,
          "sales_24h": 0
        },
        {
          "ts": "2026-07-22T14:23:35.565844+00:00",
          "floor_sol": 45.9,
          "listed": 16,
          "sales_24h": 0
        },
        {
          "ts": "2026-07-22T15:02:16.341004+00:00",
          "floor_sol": 45.9,
          "listed": 16,
          "sales_24h": 0
        },
        {
          "ts": "2026-07-22T16:43:50.954175+00:00",
          "floor_sol": 45.9,
          "listed": 16,
          "sales_24h": 0
        },
        {
          "ts": "2026-07-22T17:21:49.167511+00:00",
          "floor_sol": 45.9,
          "listed": 16,
          "sales_24h": 0
        },
        {
          "ts": "2026-07-22T17:54:44.079677+00:00",
          "floor_sol": 45.9,
          "listed": 16,
          "sales_24h": 0
        },
        {
          "ts": "2026-07-22T19:06:15.806292+00:00",
          "floor_sol": 45.9,
          "listed": 16,
          "sales_24h": 0
        },
        {
          "ts": "2026-07-22T20:20:47.131312+00:00",
          "floor_sol": 46.3889,
          "listed": 15,
          "sales_24h": 0
        },
        {
          "ts": "2026-07-22T21:23:48.304090+00:00",
          "floor_sol": 46.3889,
          "listed": 15,
          "sales_24h": 0
        },
        {
          "ts": "2026-07-22T21:35:29.793185+00:00",
          "floor_sol": 46.3889,
          "listed": 15,
          "sales_24h": 0
        },
        {
          "ts": "2026-07-22T22:39:52.122057+00:00",
          "floor_sol": 46.4,
          "listed": 14,
          "sales_24h": 0
        },
        {
          "ts": "2026-07-22T23:39:46.037834+00:00",
          "floor_sol": 46.0,
          "listed": 15,
          "sales_24h": 0
        },
        {
          "ts": "2026-07-23T01:11:36.469911+00:00",
          "floor_sol": 46.0,
          "listed": 15,
          "sales_24h": 0
        },
        {
          "ts": "2026-07-23T04:33:28.367047+00:00",
          "floor_sol": 46.0,
          "listed": 15,
          "sales_24h": 0
        }
      ],
      "last_signal": "PRUDENCE",
      "current": {
        "floor_sol": 46.0,
        "floor_eur": 3128.0,
        "floor_usdc": 3576.5,
        "listed": 15,
        "avg_price_24h_sol": 6.791331166666667,
        "sales_24h": 0,
        "holders": null,
        "signal": "PRUDENCE",
        "signal_reason": "proche du plus haut historique",
        "pct_7d": null,
        "pct_30d": null,
        "updated_at": "2026-07-23T04:33:28.367047+00:00"
      },
      "ath_sol": 45.9196,
      "ath_ts": "2026-07-21T10:07:37+00:00",
      "atl_sol": 41.721,
      "atl_ts": "2026-07-20T11:34:50+00:00",
      "history_synced": true,
      "synced_at": "2026-07-23T04:33:28.367047+00:00",
      "recent_tx": [
        {
          "type": "bid",
          "type_label": "Offre",
          "price_sol": 44.201,
          "ts": "2026-07-23T04:33:23+00:00"
        },
        {
          "type": "poolUpdate",
          "type_label": "poolUpdate",
          "price_sol": 44.201,
          "ts": "2026-07-23T04:33:23+00:00"
        },
        {
          "type": "bid",
          "type_label": "Offre",
          "price_sol": 45.131,
          "ts": "2026-07-23T04:32:53+00:00"
        },
        {
          "type": "poolUpdate",
          "type_label": "poolUpdate",
          "price_sol": 45.131,
          "ts": "2026-07-23T04:32:53+00:00"
        },
        {
          "type": "bid",
          "type_label": "Offre",
          "price_sol": 45.13,
          "ts": "2026-07-23T04:32:52+00:00"
        }
      ],
      "synced_back_to": null,
      "history_complete": false,
      "sync_offset": 15100
    },
    "the_reflection_of_love": {
      "label": "Reflection",
      "history": [
        {
          "ts": "2026-07-22T11:20:36.650123+00:00",
          "floor_sol": 13.7,
          "listed": 39,
          "sales_24h": 0
        },
        {
          "ts": "2026-07-22T12:55:52.693012+00:00",
          "floor_sol": 13.7,
          "listed": 39,
          "sales_24h": 0
        },
        {
          "ts": "2026-07-22T12:59:20.715598+00:00",
          "floor_sol": 13.7,
          "listed": 39,
          "sales_24h": 0
        },
        {
          "ts": "2026-07-22T14:23:35.565844+00:00",
          "floor_sol": 13.7,
          "listed": 39,
          "sales_24h": 0
        },
        {
          "ts": "2026-07-22T15:02:16.341004+00:00",
          "floor_sol": 13.7,
          "listed": 39,
          "sales_24h": 0
        },
        {
          "ts": "2026-07-22T16:43:50.954175+00:00",
          "floor_sol": 13.799,
          "listed": 38,
          "sales_24h": 1
        },
        {
          "ts": "2026-07-22T17:21:49.167511+00:00",
          "floor_sol": 13.799,
          "listed": 38,
          "sales_24h": 1
        },
        {
          "ts": "2026-07-22T17:54:44.079677+00:00",
          "floor_sol": 13.8,
          "listed": 37,
          "sales_24h": 1
        },
        {
          "ts": "2026-07-22T19:06:15.806292+00:00",
          "floor_sol": 13.8,
          "listed": 37,
          "sales_24h": 0
        },
        {
          "ts": "2026-07-22T20:20:47.131312+00:00",
          "floor_sol": 13.8,
          "listed": 37,
          "sales_24h": 0
        },
        {
          "ts": "2026-07-22T21:23:48.304090+00:00",
          "floor_sol": 13.8,
          "listed": 37,
          "sales_24h": 0
        },
        {
          "ts": "2026-07-22T21:35:29.793185+00:00",
          "floor_sol": 13.8,
          "listed": 37,
          "sales_24h": 0
        },
        {
          "ts": "2026-07-22T22:39:52.122057+00:00",
          "floor_sol": 14.22,
          "listed": 36,
          "sales_24h": 0
        },
        {
          "ts": "2026-07-22T23:39:46.037834+00:00",
          "floor_sol": 14.2199,
          "listed": 37,
          "sales_24h": 0
        },
        {
          "ts": "2026-07-23T01:11:36.469911+00:00",
          "floor_sol": 14.2199,
          "listed": 37,
          "sales_24h": 0
        },
        {
          "ts": "2026-07-23T04:33:28.367047+00:00",
          "floor_sol": 14.22,
          "listed": 37,
          "sales_24h": 0
        }
      ],
      "last_signal": "PRUDENCE",
      "current": {
        "floor_sol": 14.22,
        "floor_eur": 966.96,
        "floor_usdc": 1105.61,
        "listed": 37,
        "avg_price_24h_sol": 1.6269711111111111,
        "sales_24h": 0,
        "holders": null,
        "signal": "PRUDENCE",
        "signal_reason": "proche du plus haut historique",
        "pct_7d": null,
        "pct_30d": null,
        "updated_at": "2026-07-23T04:33:28.367047+00:00"
      },
      "ath_sol": 13.7,
      "ath_ts": "2026-07-22T15:12:09+00:00",
      "atl_sol": 13.399,
      "atl_ts": "2026-07-20T01:56:25+00:00",
      "history_synced": true,
      "synced_at": "2026-07-23T04:33:28.367047+00:00",
      "recent_tx": [
        {
          "type": "bid",
          "type_label": "Offre",
          "price_sol": 13.4761,
          "ts": "2026-07-23T04:33:11+00:00"
        },
        {
          "type": "poolUpdate",
          "type_label": "poolUpdate",
          "price_sol": 13.4761,
          "ts": "2026-07-23T04:33:11+00:00"
        },
        {
          "type": "bid",
          "type_label": "Offre",
          "price_sol": 13.4651,
          "ts": "2026-07-23T04:32:13+00:00"
        },
        {
          "type": "poolUpdate",
          "type_label": "poolUpdate",
          "price_sol": 13.4651,
          "ts": "2026-07-23T04:32:13+00:00"
        },
        {
          "type": "bid",
          "type_label": "Offre",
          "price_sol": 13.465,
          "ts": "2026-07-23T04:31:25+00:00"
        }
      ],
      "synced_back_to": null,
      "history_complete": false,
      "sync_offset": 15100
    },
    "tomorrowland_love_unity": {
      "label": "Symbol",
      "history": [
        {
          "ts": "2026-07-22T11:20:36.650123+00:00",
          "floor_sol": 1.95,
          "listed": 110,
          "sales_24h": 2
        },
        {
          "ts": "2026-07-22T12:55:52.693012+00:00",
          "floor_sol": 1.95,
          "listed": 109,
          "sales_24h": 4
        },
        {
          "ts": "2026-07-22T14:23:35.565844+00:00",
          "floor_sol": 1.95,
          "listed": 109,
          "sales_24h": 0
        },
        {
          "ts": "2026-07-22T15:02:16.341004+00:00",
          "floor_sol": 1.95,
          "listed": 108,
          "sales_24h": 1
        },
        {
          "ts": "2026-07-22T16:43:50.954175+00:00",
          "floor_sol": 1.95,
          "listed": 107,
          "sales_24h": 0
        },
        {
          "ts": "2026-07-22T17:21:49.167511+00:00",
          "floor_sol": 1.95,
          "listed": 107,
          "sales_24h": 0
        },
        {
          "ts": "2026-07-22T17:54:44.079677+00:00",
          "floor_sol": 1.95,
          "listed": 106,
          "sales_24h": 1
        },
        {
          "ts": "2026-07-22T19:06:15.806292+00:00",
          "floor_sol": 1.939,
          "listed": 107,
          "sales_24h": 2
        },
        {
          "ts": "2026-07-22T20:20:47.131312+00:00",
          "floor_sol": 1.939,
          "listed": 108,
          "sales_24h": 0
        },
        {
          "ts": "2026-07-22T21:23:48.304090+00:00",
          "floor_sol": 1.939,
          "listed": 108,
          "sales_24h": 0
        },
        {
          "ts": "2026-07-22T21:35:29.793185+00:00",
          "floor_sol": 1.939,
          "listed": 108,
          "sales_24h": 0
        },
        {
          "ts": "2026-07-22T22:39:52.122057+00:00",
          "floor_sol": 1.939,
          "listed": 108,
          "sales_24h": 0
        },
        {
          "ts": "2026-07-22T23:39:46.037834+00:00",
          "floor_sol": 1.9345,
          "listed": 109,
          "sales_24h": 1
        },
        {
          "ts": "2026-07-23T01:11:36.469911+00:00",
          "floor_sol": 1.9388,
          "listed": 109,
          "sales_24h": 0
        },
        {
          "ts": "2026-07-23T04:33:28.367047+00:00",
          "floor_sol": 1.9389,
          "listed": 109,
          "sales_24h": 0
        }
      ],
      "last_signal": "SURVEILLER",
      "current": {
        "floor_sol": 1.9389,
        "floor_eur": 131.85,
        "floor_usdc": 150.75,
        "listed": 109,
        "avg_price_24h_sol": 0.8323736666666667,
        "sales_24h": 0,
        "holders": null,
        "signal": "SURVEILLER",
        "signal_reason": "Pas de mouvement net.",
        "pct_7d": null,
        "pct_30d": null,
        "updated_at": "2026-07-23T04:33:28.367047+00:00"
      },
      "ath_sol": 1.95,
      "ath_ts": "2026-07-22T12:24:46+00:00",
      "atl_sol": 1.9,
      "atl_ts": "2026-07-21T11:57:13+00:00",
      "history_synced": true,
      "synced_at": "2026-07-23T04:33:28.367047+00:00",
      "recent_tx": [
        {
          "type": "list",
          "type_label": "Mise en vente",
          "price_sol": 1.9388,
          "ts": "2026-07-23T04:33:17+00:00"
        },
        {
          "type": "list",
          "type_label": "Mise en vente",
          "price_sol": 1.9389,
          "ts": "2026-07-23T04:32:22+00:00"
        },
        {
          "type": "list",
          "type_label": "Mise en vente",
          "price_sol": 1.9399,
          "ts": "2026-07-23T04:32:18+00:00"
        },
        {
          "type": "list",
          "type_label": "Mise en vente",
          "price_sol": 1.9334,
          "ts": "2026-07-23T04:31:34+00:00"
        },
        {
          "type": "list",
          "type_label": "Mise en vente",
          "price_sol": 1.9344,
          "ts": "2026-07-23T04:31:18+00:00"
        }
      ],
      "synced_back_to": null,
      "history_complete": false,
      "sync_offset": 15100
    }
  },
  "last_update": "2026-07-23T04:33:28.367047+00:00",
  "sol_eur": 68.0,
  "sol_usdc": 77.75,
  "total_holders_naive": null
}